tkitSimhash/__init__.py
tkitSimhash/simHash.py
tkitSimhash-0.0.1.9.dist-info/METADATA
tkitSimhash-0.0.1.9.dist-info/WHEEL
tkitSimhash-0.0.1.9.dist-info/top_level.txt
tkitSimhash-0.0.1.9.dist-info/RECORD
