Metadata-Version: 2.1
Name: tkitSimhash
Version: 0.0.1.9
Summary: # Remove duplicates 重复内容筛选 tkitSimhash zh    根据经验，一般当两个文档特征字之间的汉明距离小于 3， 就可以判定两个文档相似。《数学之美》一书中，在讲述信息指纹时对这种算法有详细的介绍。   ```python  from tkitSimhash import simHash sim=simHash() text1 = """' , in Valve's absence, the modern slew of co-op zombie games have not
Home-page: https://terrychanorg.jetbrains.space/p/tkittools/repositories/tkitRemoveDuplicates/files/master/README.md
Author: Terry Chan
Author-email: napoler2008@gmail.com
License: UNKNOWN
Platform: UNKNOWN
Requires-Dist: jieba (>=0.42.1)
Requires-Dist: simhash (==2.1.2)
Requires-Dist: nltk (>=3.6)
Requires-Dist: pytest (==7.1.3)
